<repast.simphony.chart2.engine.TimeSeriesChartDescriptor simphonyVersion="2.8.0">
  <name>Prevalence</name>
  <dataSet>PrevalenceData</dataSet>
  <xAxisLabel>Time(days)</xAxisLabel>
  <yAxisLabel>Fraction of Agents HCV Antibody+</yAxisLabel>
  <chartTitle>Prevalence</chartTitle>
  <type>TIME_SERIES</type>
  <background>
    <red>192</red>
    <green>192</green>
    <blue>192</blue>
    <alpha>255</alpha>
  </background>
  <gridLineColor>
    <red>255</red>
    <green>255</green>
    <blue>255</blue>
    <alpha>255</alpha>
  </gridLineColor>
  <showGrid>true</showGrid>
  <showLegend>true</showLegend>
  <seriesIds>
    <entry>
      <string>prevalence_Suburban</string>
      <SeriesData>
        <label>Suburban</label>
      </SeriesData>
    </entry>
    <entry>
      <string>prevalence_City</string>
      <SeriesData>
        <label>City</label>
      </SeriesData>
    </entry>
    <entry>
      <string>prevalence_Female</string>
      <SeriesData>
        <label>Female</label>
      </SeriesData>
    </entry>
    <entry>
      <string>prevalence_ALL</string>
      <SeriesData>
        <label>ALL</label>
      </SeriesData>
    </entry>
    <entry>
      <string>prevalence_AgeLEQ30</string>
      <SeriesData>
        <label>Young</label>
      </SeriesData>
    </entry>
    <entry>
      <string>prevalence_Black</string>
      <SeriesData>
        <label>AfrAm</label>
      </SeriesData>
    </entry>
    <entry>
      <string>prevalence_NonHR</string>
      <SeriesData>
        <label>NonHR</label>
      </SeriesData>
    </entry>
    <entry>
      <string>prevalence_HR</string>
      <SeriesData>
        <label>HarmReduction</label>
      </SeriesData>
    </entry>
    <entry>
      <string>prevalence_Hispanic</string>
      <SeriesData>
        <label>Hispanic</label>
      </SeriesData>
    </entry>
    <entry>
      <string>prevalence_Male</string>
      <SeriesData>
        <label>Male</label>
      </SeriesData>
    </entry>
    <entry>
      <string>prevalence_NHWhite</string>
      <SeriesData>
        <label>NHWhite</label>
      </SeriesData>
    </entry>
  </seriesIds>
  <dataValueIds/>
  <plotRangeLength>-1</plotRangeLength>
</repast.simphony.chart2.engine.TimeSeriesChartDescriptor>